SMF.py
SMF_torch.py
__init__.py
SupervisedMF-0.0.4.dist-info/LICENSE
SupervisedMF-0.0.4.dist-info/METADATA
SupervisedMF-0.0.4.dist-info/WHEEL
SupervisedMF-0.0.4.dist-info/top_level.txt
SupervisedMF-0.0.4.dist-info/RECORD
