Metadata-Version: 2.1
Name: SupervisedMF
Version: 0.0.4
Summary: A package for various supervised matrix factorization methods
Author-email: Agam Goyal <agamg2@illinois.edu>, Yi Wei <ywei224@wisc.edu>, Hanbaek Lyu <hlyu@math.wisc.edu>
Maintainer-email: Agam Goyal <agamg2@illinois.edu>
Project-URL: Homepage, https://github.com/ljw9510/SMF/tree/main
Project-URL: Issues, https://github.com/ljw9510/SMF/issues
Keywords: supervised matrix factorization,matrix factorization,dimensionality reduction,low-rank compression,classification
Classifier: Programming Language :: Python :: 3
Classifier: License :: OSI Approved :: MIT License
Classifier: Operating System :: OS Independent
Requires-Python: >=3.10
License-File: LICENSE
Requires-Dist: numpy >=2.0.0
Requires-Dist: scipy >=1.13.0
Requires-Dist: scikit-learn >=1.5.1
Requires-Dist: matplotlib >=3.9.0
Requires-Dist: pandas >=2.2.2
Requires-Dist: seaborn >=0.13.0
Requires-Dist: tqdm >=4.66.4
